setup.py
materialgirl/__init__.py
materialgirl/materializer.py
materialgirl.egg-info/PKG-INFO
materialgirl.egg-info/SOURCES.txt
materialgirl.egg-info/dependency_links.txt
materialgirl.egg-info/entry_points.txt
materialgirl.egg-info/requires.txt
materialgirl.egg-info/top_level.txt
materialgirl/storage/__init__.py
materialgirl/storage/memory.py
materialgirl/storage/redis.py
tests/__init__.py
tests/base.py
tests/test_material_girl.py
tests/storage/__init__.py
tests/storage/test_base_storage.py
tests/storage/test_in_memory_storage.py
tests/storage/test_redis_storage.py