Metadata-Version: 1.1
Name: materialgirl
Version: 0.4.2
Summary: MaterialGirl is a library to keep materialized views and consolidations up-to-date.
Home-page: http://materialgirllib.com
Author: Bernardo Heynemann
Author-email: heynemann@gmail.com
License: MIT
Keywords: mysql database redis
Platform: UNKNOWN
Classifier: Development Status :: 4 - Beta
Classifier: Intended Audience :: Developers
Classifier: License :: OSI Approved :: MIT License
Classifier: Natural Language :: English
Classifier: Operating System :: MacOS
Classifier: Operating System :: POSIX
Classifier: Operating System :: Unix
Classifier: Operating System :: OS Independent
Classifier: Programming Language :: Python :: 2.7
Classifier: Programming Language :: Python :: 3.3
